eztemplate/__init__.py
eztemplate/__main__.py
eztemplate/version.py
eztemplate/engines/__init__.py
eztemplate/engines/empy_engine.py
eztemplate/engines/mako_engine.py
eztemplate/engines/string_formatter_engine.py
eztemplate/engines/string_template_engine.py
eztemplate-0.3.0.dist-info/DESCRIPTION.rst
eztemplate-0.3.0.dist-info/METADATA
eztemplate-0.3.0.dist-info/RECORD
eztemplate-0.3.0.dist-info/WHEEL
eztemplate-0.3.0.dist-info/entry_points.txt
eztemplate-0.3.0.dist-info/metadata.json
eztemplate-0.3.0.dist-info/top_level.txt
