Metadata-Version: 2.0
Name: eztemplate
Version: 0.3.0
Summary: Simple templating program to generate plain text (like config files) from name-value pairs.
Home-page: https://github.com/blubberdiblub/eztemplate/
Author: Niels Boehm
Author-email: blubberdiblub@gmail.com
License: MIT
Keywords: templating,text
Platform: UNKNOWN
Classifier: Development Status :: 4 - Beta
Classifier: Environment :: Console
Classifier: Intended Audience :: End Users/Desktop
Classifier: Intended Audience :: System Administrators
Classifier: License :: OSI Approved :: MIT License
Classifier: Operating System :: OS Independent
Classifier: Programming Language :: Python
Classifier: Programming Language :: Python :: 2
Classifier: Programming Language :: Python :: 2.7
Classifier: Programming Language :: Python :: 3
Classifier: Topic :: System :: Systems Administration
Classifier: Topic :: Text Processing :: General
Classifier: Topic :: Utilities
Requires-Dist: argparse
Provides-Extra: empy
Requires-Dist: empy; extra == 'empy'
Provides-Extra: mako
Requires-Dist: mako; extra == 'mako'
